bblib/__init__.py
bblib/methods.py
bblib/models.py
bblib/utils.py
bblib-3.1.0.dist-info/LICENSE
bblib-3.1.0.dist-info/METADATA
bblib-3.1.0.dist-info/WHEEL
bblib-3.1.0.dist-info/RECORD
